mongodb_connect/__init__.py
mongodb_connect/mongo_crud.py
tests/__init__.py
pydb_connector-0.0.4.dist-info/METADATA
pydb_connector-0.0.4.dist-info/WHEEL
pydb_connector-0.0.4.dist-info/top_level.txt
pydb_connector-0.0.4.dist-info/RECORD
