Metadata-Version: 2.1
Name: PyDB_Connector
Version: 0.0.4
Summary: A Python package for connecting with databases.
Home-page: https://github.com/anshu1016/MLOPS_Project
Author: anshu1016
Author-email: arunshukla98710@gmail.com
License: MIT
Project-URL: Bug Tracker, https://github.com/anshu1016/MLOPS_Project/issues
Classifier: Programming Language :: Python :: 3.7
Classifier: Programming Language :: Python :: 3.8
Classifier: Programming Language :: Python :: 3.9
Classifier: Operating System :: OS Independent
Requires-Python: >=3.7
Requires-Dist: pymongo
Requires-Dist: dnspython
Requires-Dist: pandas
Requires-Dist: numpy
Requires-Dist: ensure
Provides-Extra: testing
Requires-Dist: pytest>=7.1.3; extra == "testing"
Requires-Dist: mypy>=0.971; extra == "testing"
Requires-Dist: flake8>=5.0.4; extra == "testing"
Requires-Dist: tox>=3.25.1; extra == "testing"
Requires-Dist: black>=22.8.0; extra == "testing"
